Metadata-Version: 2.1
Name: bitbucket-code-insight-reports
Version: 0.0.11
Summary: Upload reports to BitBucket server for use with the Code Insights feature
Home-page: https://github.com/tomtom-international/bitbucket-code-insight-reports
Author: Eugene Davis
Author-email: eugene.davis@tomtom.com
License: Apache Software License 2.0
Keywords: bitbucket_code_insight_reports
Platform: UNKNOWN
Classifier: Development Status :: 2 - Pre-Alpha
Classifier: Intended Audience :: Developers
Classifier: License :: OSI Approved :: Apache Software License
Classifier: Natural Language :: English
Classifier: Programming Language :: Python :: 3
Classifier: Programming Language :: Python :: 3.5
Classifier: Programming Language :: Python :: 3.6
Classifier: Programming Language :: Python :: 3.7
